[
  {
    "full_name": "golang-standards/project-layout",
    "stargazers_count": 51990,
    "open_issues_count": 92,
    "forks_count": 5304
  },
  {
    "full_name": "x-sushant-x/Rate-Shield",
    "stargazers_count": 157,
    "open_issues_count": 7,
    "forks_count": 13
  },
  {
    "full_name": "AFK-AlignedFamKernel/afk_monorepo",
    "stargazers_count": 19,
    "open_issues_count": 44,
    "forks_count": 58
  },
  {
    "full_name": "systemdesign42/system-design",
    "stargazers_count": 15282,
    "open_issues_count": 0,
    "forks_count": 1567
  },
  {
    "full_name": "keep-starknet-strange/shinigami",
    "stargazers_count": 68,
    "open_issues_count": 12,
    "forks_count": 63
  },
  {
    "full_name": "practical-tutorials/project-based-learning",
    "stargazers_count": 224905,
    "open_issues_count": 217,
    "forks_count": 29401
  },
  {
    "full_name": "microsoft/generative-ai-for-beginners",
    "stargazers_count": 78705,
    "open_issues_count": 17,
    "forks_count": 40918
  },
  {
    "full_name": "Hyle-org/hyle",
    "stargazers_count": 46,
    "open_issues_count": 22,
    "forks_count": 24
  },
  {
    "full_name": "MhdSadd/scrapper-framework",
    "stargazers_count": 1,
    "open_issues_count": 0,
    "forks_count": 0
  },
  {
    "full_name": "CodingChallengesFYI/SharedSolutions",
    "stargazers_count": 2866,
    "open_issues_count": 24,
    "forks_count": 630
  },
  {
    "full_name": "codecrafters-io/build-your-own-x",
    "stargazers_count": 373646,
    "open_issues_count": 376,
    "forks_count": 34755
  },
  {
    "full_name": "EddieHubCommunity/RepoRater",
    "stargazers_count": 156,
    "open_issues_count": 23,
    "forks_count": 35
  },
  {
    "full_name": "illacloud/illa-builder",
    "stargazers_count": 11978,
    "open_issues_count": 41,
    "forks_count": 1132
  },
  {
    "full_name": "stenciljs/core",
    "stargazers_count": 12751,
    "open_issues_count": 286,
    "forks_count": 804
  },
  {
    "full_name": "calcom/cal.com",
    "stargazers_count": 35856,
    "open_issues_count": 1084,
    "forks_count": 9198
  },
  {
    "full_name": "go-gorm/gorm",
    "stargazers_count": 38027,
    "open_issues_count": 456,
    "forks_count": 3998
  },
  {
    "full_name": "SigNoz/signoz",
    "stargazers_count": 21557,
    "open_issues_count": 1481,
    "forks_count": 1515
  },
  {
    "full_name": "makeplane/plane",
    "stargazers_count": 35438,
    "open_issues_count": 474,
    "forks_count": 2195
  },
  {
    "full_name": "medusajs/medusa",
    "stargazers_count": 28648,
    "open_issues_count": 156,
    "forks_count": 3195
  },
  {
    "full_name": "mattermost/mattermost",
    "stargazers_count": 32355,
    "open_issues_count": 969,
    "forks_count": 7727
  },
  {
    "full_name": "avgupta456/github-trends",
    "stargazers_count": 16055,
    "open_issues_count": 46,
    "forks_count": 108
  },
  {
    "full_name": "JohnCrickett/SystemDesign",
    "stargazers_count": 561,
    "open_issues_count": 0,
    "forks_count": 69
  },
  {
    "full_name": "avelino/awesome-go",
    "stargazers_count": 142239,
    "open_issues_count": 121,
    "forks_count": 12244
  },
  {
    "full_name": "gin-gonic/gin",
    "stargazers_count": 81843,
    "open_issues_count": 861,
    "forks_count": 8180
  },
  {
    "full_name": "golang/go",
    "stargazers_count": 127323,
    "open_issues_count": 9419,
    "forks_count": 17981
  },
  {
    "full_name": "shadcn-ui/ui",
    "stargazers_count": 85717,
    "open_issues_count": 1741,
    "forks_count": 5791
  },
  {
    "full_name": "shadcn-ui/taxonomy",
    "stargazers_count": 18898,
    "open_issues_count": 213,
    "forks_count": 2636
  },
  {
    "full_name": "kunal-kushwaha/DSA-Bootcamp-Java",
    "stargazers_count": 18846,
    "open_issues_count": 567,
    "forks_count": 11864
  },
  {
    "full_name": "ArslanYM/StarterHive",
    "stargazers_count": 213,
    "open_issues_count": 53,
    "forks_count": 197
  },
  {
    "full_name": "lukasz-madon/awesome-remote-job",
    "stargazers_count": 37649,
    "open_issues_count": 13,
    "forks_count": 4114
  }
]